LICENSE.txt
MANIFEST.in
NOTICES
README.md
setup.py
claid/CLAID.py
claid/__init__.py
claid/claid_cli.py
claid/config_reload_test.py
claid/module_injection_test.py
claid/plot.py
claid/py_claid
claid/py_claid.py
claid/test.py
claid/test_config.json
claid.egg-info/PKG-INFO
claid.egg-info/SOURCES.txt
claid.egg-info/dependency_links.txt
claid.egg-info/entry_points.txt
claid.egg-info/requires.txt
claid.egg-info/top_level.txt
claid/_solib_k8/__init__.py
claid/_solib_k8/libexternal_Scom_Ugithub_Ugrpc_Ugrpc_Slibgrpc.so
claid/claid_cli_utils/__init__.py
claid/claid_cli_utils/check_protoc.py
claid/claid_cli_utils/create_package.py
claid/data_collection/__init__.py
claid/data_collection/load/__init__.py
claid/data_collection/load/load_sensor_data.py
claid/data_collection/plot/__init__.py
claid/data_collection/plot/acceleration_view.py
claid/data_collection/plot/gyroscope_view.py
claid/data_collection/plot/heartrate_view.py
claid/data_collection/plot/plot_acceleration_data.py
claid/data_collection/plot/plot_battery_data.py
claid/data_collection/plot/plot_heart_rate_data.py
claid/dispatch/__init__.py
claid/dispatch/core/__init__.py
claid/dispatch/core/Darwin/arm64/libclaid_capi.dylib
claid/dispatch/core/Darwin/x86_64/libclaid_capi.dylib
claid/dispatch/core/Linux/arm64/libclaid_capi.so
claid/dispatch/core/Linux/x86_64/libclaid_capi.so
claid/dispatch/proto/__init__.py
claid/dispatch/proto/claidservice_pb2.py
claid/dispatch/proto/claidservice_pb2.pyi
claid/dispatch/proto/claidservice_pb2_grpc.py
claid/dispatch/proto/layerdata_pb2.py
claid/dispatch/proto/layerdata_pb2.pyi
claid/dispatch/proto/layerdata_pb2_grpc.py
claid/dispatch/proto/sensor_data_types_pb2.py
claid/dispatch/proto/sensor_data_types_pb2.pyi
claid/dispatch/proto/sensor_data_types_pb2_grpc.py
claid/helpers/__init__.py
claid/helpers/c_binding_helpers.py
claid/local_dispatching/__init__.py
claid/local_dispatching/module_dispatcher.py
claid/local_dispatching/module_injector.py
claid/local_dispatching/module_manager.py
claid/logger/__init__.py
claid/logger/logger.py
claid/module/__init__.py
claid/module/abstract_subscriber.py
claid/module/channel.py
claid/module/channel_access_rights.py
