Metadata-Version: 2.1
Name: claid
Version: 0.6.2
Summary: CLAID Python package (PyCLAID)
Home-page: https://claid.ch
Author: Patrick Langer
Author-email: planger@ethz.ch
License: Apache 2
Classifier: Development Status :: 4 - Beta
Classifier: Intended Audience :: Science/Research
Classifier: Intended Audience :: Developers
Classifier: Intended Audience :: Healthcare Industry
Classifier: Intended Audience :: Information Technology
Classifier: License :: OSI Approved :: Apache Software License
Classifier: Operating System :: Android
Classifier: Operating System :: MacOS
Classifier: Operating System :: POSIX :: Linux
Classifier: Operating System :: Unix
Classifier: Topic :: Scientific/Engineering :: Artificial Intelligence
Classifier: Programming Language :: Python :: 3.7
Classifier: Programming Language :: Python :: 3.8
Classifier: Programming Language :: Python :: 3.9
Requires-Python: >=3.7
License-File: LICENSE.txt
License-File: NOTICES
Requires-Dist: protobuf==4.25.3
Requires-Dist: grpcio==1.59.3
Requires-Dist: numpy
